ENRGAI/__init__.py
ENRGAI/dataset_retriever.py
ENRGAI-1.0.1.dist-info/LICENSE.txt
ENRGAI-1.0.1.dist-info/METADATA
ENRGAI-1.0.1.dist-info/WHEEL
ENRGAI-1.0.1.dist-info/top_level.txt
ENRGAI-1.0.1.dist-info/RECORD
