Metadata-Version: 2.1
Name: ENRGAI
Version: 1.0.1
Summary: A library to fetch and merge data from ENRG-AI APIs.
Author: Behdad Ehsani
Author-email: behdad.ehsani@enrg-ai.ca
Classifier: License :: OSI Approved :: MIT License
Classifier: Programming Language :: Python :: 3
Classifier: Programming Language :: Python :: 3.7
Classifier: Programming Language :: Python :: 3.8
Classifier: Programming Language :: Python :: 3.9
Classifier: Programming Language :: Python :: 3.10
Classifier: Programming Language :: Python :: 3.11
License-File: LICENSE.txt
Requires-Dist: requests
Requires-Dist: pandas
